hideandseek/__init__.py
hideandseek/dataset.py
hideandseek/eval.py
hideandseek/evaluation.py
hideandseek/fv.py
hideandseek/loss.py
hideandseek/model.py
hideandseek/plot.py
hideandseek/trainer.py
hideandseek/utils.py
hideandseek/validation.py
hideandseek-0.3.27.dist-info/LICENSE
hideandseek-0.3.27.dist-info/METADATA
hideandseek-0.3.27.dist-info/WHEEL
hideandseek-0.3.27.dist-info/top_level.txt
hideandseek-0.3.27.dist-info/RECORD
