Metadata-Version: 2.1
Name: hideandseek
Version: 0.3.27
Summary: library for deep learning and privacy preserving deep learning
Home-page: https://github.com/jsyoo61/hideandseek
Author: JaeSung Yoo
Author-email: jsyoo61@unc.edu
Classifier: Programming Language :: Python :: 3
Classifier: License :: OSI Approved :: MIT License
Classifier: Operating System :: OS Independent
Requires-Python: >=3.6
License-File: LICENSE
Requires-Dist: numpy
Requires-Dist: pandas
Requires-Dist: matplotlib
Requires-Dist: hydra-core
Requires-Dist: tools-jsyoo61
